python_monasca_events-0.0.2.dist-info/METADATA
python_monasca_events-0.0.2.dist-info/entry_points.txt
python_monasca_events-0.0.2.dist-info/RECORD
python_monasca_events-0.0.2.dist-info/pbr.json
python_monasca_events-0.0.2.dist-info/metadata.json
python_monasca_events-0.0.2.dist-info/DESCRIPTION.rst
python_monasca_events-0.0.2.dist-info/WHEEL
python_monasca_events-0.0.2.dist-info/top_level.txt
monasca_events/ksclient.py
monasca_events/events_shell.py
monasca_events/exc.py
monasca_events/client.py
monasca_events/__init__.py
monasca_events/openstack/__init__.py
monasca_events/openstack/common/gettextutils.py
monasca_events/openstack/common/jsonutils.py
monasca_events/openstack/common/importutils.py
monasca_events/openstack/common/timeutils.py
monasca_events/openstack/common/strutils.py
monasca_events/openstack/common/__init__.py
monasca_events/openstack/common/apiclient/base.py
monasca_events/openstack/common/apiclient/__init__.py
monasca_events/openstack/common/apiclient/exceptions.py
monasca_events/openstack/common/py3kcompat/urlutils.py
monasca_events/openstack/common/py3kcompat/__init__.py
monasca_events/common/http.py
monasca_events/common/utils.py
monasca_events/common/monasca_manager.py
monasca_events/common/__init__.py
monasca_events/v2_0/events.py
monasca_events/v2_0/events_shell.py
monasca_events/v2_0/client.py
monasca_events/v2_0/__init__.py
