Metadata-Version: 2.0
Name: python-monasca-events
Version: 0.0.2
Summary: Monasca Events API Client Library
Home-page: https://github.com/hpcloud-mon/python-monasca-events
Author: Hewlett-Packard
Author-email: UNKNOWN
License: UNKNOWN
Platform: UNKNOWN
Classifier: Environment :: Console
Classifier: Intended Audience :: Information Technology
Classifier: Intended Audience :: System Administrators
Classifier: License :: OSI Approved :: Apache Software License
Classifier: Operating System :: POSIX :: Linux
Classifier: Programming Language :: Python
Classifier: Programming Language :: Python :: 2
Classifier: Programming Language :: Python :: 2.7
Classifier: Programming Language :: Python :: 2.6
Classifier: Programming Language :: Python :: 3
Classifier: Programming Language :: Python :: 3.3
Requires-Dist: six
Requires-Dist: argparse
Requires-Dist: babel
Requires-Dist: iso8601 (>=0.1.9)
Requires-Dist: pbr (>=0.11,<2.0)
Requires-Dist: PrettyTable (>=0.7,<0.8)
Requires-Dist: python-keystoneclient (>=0.9.0)
Requires-Dist: PyYAML (>=3.1.0)
Requires-Dist: requests (>=1.1)
